geventhttpclient_wheels-1.3.1.dev3.dist-info/LICENSE-MIT
geventhttpclient_wheels-1.3.1.dev3.dist-info/top_level.txt
geventhttpclient_wheels-1.3.1.dev3.dist-info/RECORD
geventhttpclient_wheels-1.3.1.dev3.dist-info/METADATA
geventhttpclient_wheels-1.3.1.dev3.dist-info/WHEEL
geventhttpclient/response.py
geventhttpclient/header.py
geventhttpclient/url.py
geventhttpclient/_parser.cpython-35m-x86_64-linux-gnu.so
geventhttpclient/connectionpool.py
geventhttpclient/__init__.py
geventhttpclient/useragent.py
geventhttpclient/httplib.py
geventhttpclient/client.py
geventhttpclient/tests/server.key
geventhttpclient/tests/test_httplib.py
geventhttpclient/tests/test_keep_alive.py
geventhttpclient/tests/oncert.pem
geventhttpclient/tests/test_ssl.py
geventhttpclient/tests/test_parser.py
geventhttpclient/tests/test_headers.py
geventhttpclient/tests/test_url.py
geventhttpclient/tests/test_no_module_ssl.py
geventhttpclient/tests/server.crt
geventhttpclient/tests/test_useragent.py
geventhttpclient/tests/test_network_failures.py
geventhttpclient/tests/test_client.py
