Metadata-Version: 2.1
Name: geventhttpclient-wheels
Version: 1.3.1.dev3
Summary: Pre-built wheels for geventhttpclient
Home-page: http://github.com/gwik/geventhttpclient
Author: Antonin Amand (Fork maintained by the Locust project)
Author-email: antonin.amand@gmail.com
License: LICENSE-MIT
Platform: UNKNOWN
Requires-Dist: gevent (>=0.13)
Requires-Dist: certifi
Requires-Dist: six
